MANIFEST.in
README.md
requirements.txt
setup.cfg
setup.py
exa/__init__.py
exa/_version.py
exa/static.py
exa/typed.py
exa.egg-info/PKG-INFO
exa.egg-info/SOURCES.txt
exa.egg-info/dependency_links.txt
exa.egg-info/not-zip-safe
exa.egg-info/requires.txt
exa.egg-info/top_level.txt
exa/conf/logging.yml
exa/core/__init__.py
exa/core/container.py
exa/core/editor.py
exa/core/error.py
exa/core/numerical.py
exa/core/tests/__init__.py
exa/core/tests/test_container.py
exa/core/tests/test_editor.py
exa/core/tests/test_error.py
exa/core/tests/test_numerical.py
exa/static/constants.json
exa/static/isotopes.json
exa/static/parser.bz2
exa/static/units.json.bz2
exa/static/version.txt
exa/tests/__init__.py
exa/tests/test_static.py
exa/tests/test_typed.py
exa/util/__init__.py
exa/util/constants.py
exa/util/io.py
exa/util/isotopes.py
exa/util/mpl.py
exa/util/nbvars.py
exa/util/units.py
exa/util/utility.py
exa/util/tests/__init__.py
exa/util/tests/test_constants.py
exa/util/tests/test_io.py
exa/util/tests/test_isotopes.py
exa/util/tests/test_nbvars.py
exa/util/tests/test_units.py
exa/util/tests/test_utility.py