Metadata-Version: 1.2
Name: exa
Version: 0.5.25
Summary: A framework for data engineering and science
Home-page: UNKNOWN
Author: The Exa Analytics development team
Author-email: exa.data.analytics@gmail.com
License: Apache License Version 2.0
Project-URL: Bug Tracker, https://github.com/exa-analytics/exa/issues
Project-URL: Documentation, https://exa-analytics.github.io/exa/
Project-URL: Source Code, https://github.com/exa-analytics/exa
Platform: UNKNOWN
Classifier: Intended Audience :: Developers
Classifier: Intended Audience :: Science/Research
Classifier: License :: OSI Approved :: Apache Software License
Classifier: Programming Language :: Python :: 3
Classifier: Natural Language :: English
